Workbook

Sheet Resumen
A2: COMPUSEARCH - DASHBOARD BASE DE DATOS, TIENDAS Y CATALOGO WEB
A3: Sistema Integrado con Imágenes, Enlaces de Tiendas y Endpoints MSW | v3.0
A5: INDICADORES CLAVE DE RENDIMIENTO (KPIs) - INVENTARIO GENERAL
A6: Indicador / KPI | B6: Valor / Resultado | C6: Origen de Datos
A7: Total Productos Registrados | B7: =COUNTA(Productos!A3:A30) | C7: Tabla Productos (Items)
A8: Total Unidades en Stock | B8: =SUM(Productos!E3:E30) | C8: Tabla Productos (Unidades)
A9: Valor Total Inventario ($) | B9: =SUM(Productos!G3:G30) | C9: Tabla Productos ($ USD)
A10: Tiendas Comercializadoras | B10: =COUNTA(Tiendas!A3:A11) | C10: Tabla Tiendas
A11: Tiendas Activas en Sistema | B11: =COUNTIF(Tiendas!D4:D11, "ACTIVO") + 1 | C11: Tabla Tiendas (Estatus ACTIVO)
A12: Usuarios Registrados | B12: =COUNTA(Usuarios!A3:A6) | C12: Tabla Usuarios
A13: Empleados Registrados | B13: =COUNTA(Empleados!A3:A5) | C13: Tabla Empleados
A14: Incidentes Pendientes | B14: =COUNTIF(Incidentes!C3:C4, "PENDIENTE") | C14: Mesa de Ayuda (Incidentes)
A15: Categorías de Hardware | B15: =COUNTA('Categorías y Endpoints'!A3:A11) | C15: Pestaña Categorías
A16: Endpoints API MSW Definidos | B16: =COUNTA('Categorías y Endpoints'!A15:A29) | C16: Pestaña Endpoints API
A19: RESUMEN DE STOCK Y VALOR DE INVENTARIO POR TIENDA / FUENTE
A20: Tienda / Fuente Comercial | B20: Productos Distintos | C20: Stock Total (Unid.) | D20: Valor Total ($) | E20: Enlace Web / Catálogo
A21: pc Factory Perú | B21: =COUNTIF(Productos!H3:H30, "pc Factory Perú") | C21: =SUMIF(Productos!H3:H30, "pc Factory Perú", Productos!E3:E30) | D21: =SUMIF(Productos!H3:H30, "pc Factory Perú", Productos!G3:G30) | E21: =HYPERLINK("https://www.pcfactory.com.pe", "Ver Web pc Factory")
A22: Grupo Compu & Visión | B22: =COUNTIF(Productos!H3:H30, "Grupo Compu & Visión") | C22: =SUMIF(Productos!H3:H30, "Grupo Compu & Visión", Productos!E3:E30) | D22: =SUMIF(Productos!H3:H30, "Grupo Compu & Visión", Productos!G3:G30) | E22: =HYPERLINK("https://compuvision.pe", "Ver Web Compu & Visión")
A23: SB Data | B23: =COUNTIF(Productos!H3:H30, "SB Data") | C23: =SUMIF(Productos!H3:H30, "SB Data", Productos!E3:E30) | D23: =SUMIF(Productos!H3:H30, "SB Data", Productos!G3:G30) | E23: =HYPERLINK("https://sbdata.com.pe", "Ver Web SB Data")
A24: Infotec Perú | B24: =COUNTIF(Productos!H3:H30, "Infotec Perú") | C24: =SUMIF(Productos!H3:H30, "Infotec Perú", Productos!E3:E30) | D24: =SUMIF(Productos!H3:H30, "Infotec Perú", Productos!G3:G30) | E24: =HYPERLINK("https://infotec.com.pe", "Ver Web Infotec")
A25: Rayotec | B25: =COUNTIF(Productos!H3:H30, "Rayotec") | C25: =SUMIF(Productos!H3:H30, "Rayotec", Productos!E3:E30) | D25: =SUMIF(Productos!H3:H30, "Rayotec", Productos!G3:G30) | E25: =HYPERLINK("https://rayotec.pe", "Ver Web Rayotec")
A26: CompuSearch Central / Norte | B26: =COUNTIF(Productos!H3:H30, "CompuSearch*") | C26: =SUMIF(Productos!H3:H30, "CompuSearch*", Productos!E3:E30) | D26: =SUMIF(Productos!H3:H30, "CompuSearch*", Productos!G3:G30) | E26: =HYPERLINK("https://compusearch.com", "Ver Portal CompuSearch")
A27: TOTAL ACUMULADO TIENDAS | B27: =SUM(B21:B26) | C27: =SUM(C21:C26) | D27: =SUM(D21:D26) | E27: -

Sheet Productos
A1: ID | B1: Vista Previa | C1: Nombre del Producto / Componente | D1: Categoría | E1: Stock | F1: Precio Unit. ($) | G1: Valor Total ($) | H1: Tienda / Fuente de Origen | I1: Ubicación / Dirección de la Tienda | J1: Estatus | K1: Enlace Foto / Imagen (URL) | L1: Enlace Web / Tienda (URL)
A3: 101 | C3: Procesador Intel Core i9-14900K 24-Cores | D3: CPU | E3: 10 | F3: 450 | G3: =E3*F3 | H3: CompuSearch Central | I3: Av. Principal 123 - San Isidro | J3: DISPONIBLE | K3: =HYPERLINK("https://m.media-amazon.com/images/I/61L2r5K2EGL._AC_SL1500_.jpg", "Ver Foto HD") | L3: =HYPERLINK("https://compusearch.com/productos/101", "Ver en CompuSearch")
A4: 102 | C4: Tarjeta Gráfica RTX 4090 24GB GDDR6X | D4: GPU | E4: 3 | F4: 1599.99 | G4: =E4*F4 | H4: CompuSearch Central | I4: Av. Principal 123 - San Isidro | J4: STOCK BAJO | K4: =HYPERLINK("https://m.media-amazon.com/images/I/71R2nN6vBfL._AC_SL1500_.jpg", "Ver Foto HD") | L4: =HYPERLINK("https://compusearch.com/productos/102", "Ver en CompuSearch")
A5: 103 | C5: Memoria RAM 32GB (2x16GB) DDR5 6000MHz | D5: RAM | E5: 25 | F5: 120.5 | G5: =E5*F5 | H5: CompuSearch Norte | I5: Plaza Mayor 456 - Los Olivos | J5: DISPONIBLE | K5: =HYPERLINK("https://m.media-amazon.com/images/I/61K5A-L+2oL._AC_SL1500_.jpg", "Ver Foto HD") | L5: =HYPERLINK("https://compusearch.com/productos/103", "Ver en CompuSearch")
A6: 104 | C6: Procesador Intel Core i5-12400F 6 Núcleos | D6: CPU | E6: 30 | F6: 183.75 | G6: =E6*F6 | H6: pc Factory Perú | I6: Plaza San Miguel / Jockey Plaza | J6: DISPONIBLE | K6: =HYPERLINK("https://m.media-amazon.com/images/I/51rP-4L2P3L._AC_SL1000_.jpg", "Ver Foto HD") | L6: =HYPERLINK("https://www.pcfactory.com.pe/producto/45231", "Ver en pc")
A7: 105 | C7: Procesador AMD Ryzen 5 5500 6 Cursos 4.2GHz | D7: CPU | E7: 17 | F7: 108 | G7: =E7*F7 | H7: pc Factory Perú | I7: Plaza San Miguel / Jockey Plaza | J7: DISPONIBLE | K7: =HYPERLINK("https://m.media-amazon.com/images/I/61vGQNUEsGL._AC_SL1200_.jpg", "Ver Foto HD") | L7: =HYPERLINK("https://www.pcfactory.com.pe/producto/46112", "Ver en pc")
A8: 106 | C8: Procesador AMD Ryzen 7 5700G 8 Cursos 4.6GHz | D8: CPU | E8: 11 | F8: 224.25 | G8: =E8*F8 | H8: pc Factory Perú | I8: Plaza San Miguel / Jockey Plaza | J8: DISPONIBLE | K8: =HYPERLINK("https://m.media-amazon.com/images/I/51f2A6M47xL._AC_SL1000_.jpg", "Ver Foto HD") | L8: =HYPERLINK("https://www.pcfactory.com.pe/producto/43009", "Ver en pc")
A9: 107 | C9: Procesador Intel Core i7-12700 12 Cursos 4.9GHz | D9: CPU | E9: 12 | F9: 405.35 | G9: =E9*F9 | H9: pc Factory Perú | I9: Plaza San Miguel / Jockey Plaza | J9: DISPONIBLE | K9: =HYPERLINK("https://m.media-amazon.com/images/I/51B-74V2cDL._AC_SL1000_.jpg", "Ver Foto HD") | L9: =HYPERLINK("https://www.pcfactory.com.pe/producto/45001", "Ver en pc")
A10: 108 | C10: Procesador AMD Ryzen 5 7600X AM5 5.3GHz | D10: CPU | E10: 6 | F10: 251.3 | G10: =E10*F10 | H10: pc Factory Perú | I10: Plaza San Miguel / Jockey Plaza | J10: DISPONIBLE | K10: =HYPERLINK("https://m.media-amazon.com/images/I/61b17L-7e5L._AC_SL1000_.jpg", "Ver Foto HD") | L10: =HYPERLINK("https://www.pcfactory.com.pe/producto/47100", "Ver en pc")
A11: 109 | C11: Tarjeta de Video GeForce RTX 3050 6GB MSI Ventus 2X | D11: GPU | E11: 23 | F11: 270.2 | G11: =E11*F11 | H11: pc Factory Perú | I11: Plaza San Miguel / Jockey Plaza | J11: DISPONIBLE | K11: =HYPERLINK("https://m.media-amazon.com/images/I/71a6P6M3C7L._AC_SL1500_.jpg", "Ver Foto HD") | L11: =HYPERLINK("https://www.pcfactory.com.pe/producto/50123", "Ver en pc")
A12: 110 | C12: Tarjeta de Video GeForce RTX 5060 8GB MSI Shadow 2X | D12: GPU | E12: 8 | F12: 459.4 | G12: =E12*F12 | H12: pc Factory Perú | I12: Plaza San Miguel / Jockey Plaza | J12: DISPONIBLE | K12: =HYPERLINK("https://m.media-amazon.com/images/I/71I3P6+bKML._AC_SL1500_.jpg", "Ver Foto HD") | L12: =HYPERLINK("https://www.pcfactory.com.pe/producto/51200", "Ver en pc")
A13: 111 | C13: Tarjeta de Video GeForce RTX 5070 12GB Asus Prime OC | D13: GPU | E13: 4 | F13: 1054 | G13: =E13*F13 | H13: pc Factory Perú | I13: Plaza San Miguel / Jockey Plaza | J13: STOCK BAJO | K13: =HYPERLINK("https://m.media-amazon.com/images/I/81R4q+nN3AL._AC_SL1500_.jpg", "Ver Foto HD") | L13: =HYPERLINK("https://www.pcfactory.com.pe/producto/52300", "Ver en pc")
A14: 112 | C14: Placa MSI MAG X870E GAMING MAX WIFI AM5 DDR5 | D14: Motherboard | E14: 2 | F14: 299 | G14: =E14*F14 | H14: Grupo Compu & Visión | I14: Galería Compuplaza - Wilson 1251 #123 | J14: STOCK BAJO | K14: =HYPERLINK("https://m.media-amazon.com/images/I/81G3+7d+C3L._AC_SL1500_.jpg", "Ver Foto HD") | L14: =HYPERLINK("https://compuvision.pe/producto/msi-x870e", "Ver en Grupo")
A15: 113 | C15: Tarjeta de Video RTX 5050 8GB Gigabyte Windforce OC | D15: GPU | E15: 10 | F15: 365 | G15: =E15*F15 | H15: Grupo Compu & Visión | I15: Galería Compuplaza - Wilson 1251 #123 | J15: DISPONIBLE | K15: =HYPERLINK("https://m.media-amazon.com/images/I/71k4B7a1wCL._AC_SL1500_.jpg", "Ver Foto HD") | L15: =HYPERLINK("https://compuvision.pe/producto/rtx-5050-gigabyte", "Ver en Grupo")
A16: 114 | C16: Placa Gigabyte B860M K Gen5 LGA 1851 DDR5 | D16: Motherboard | E16: 5 | F16: 113 | G16: =E16*F16 | H16: Grupo Compu & Visión | I16: Galería Compuplaza - Wilson 1251 #123 | J16: DISPONIBLE | K16: =HYPERLINK("https://m.media-amazon.com/images/I/81+c7B2527L._AC_SL1500_.jpg", "Ver Foto HD") | L16: =HYPERLINK("https://compuvision.pe/producto/b860m-gigabyte", "Ver en Grupo")
A17: 115 | C17: Placa Asus ROG STRIX X870E-E GAMING WIFI7 AM5 | D17: Motherboard | E17: 1 | F17: 651 | G17: =E17*F17 | H17: Grupo Compu & Visión | I17: Galería Compuplaza - Wilson 1251 #123 | J17: STOCK BAJO | K17: =HYPERLINK("https://m.media-amazon.com/images/I/81c-99C1L2L._AC_SL1500_.jpg", "Ver Foto HD") | L17: =HYPERLINK("https://compuvision.pe/producto/rog-x870e", "Ver en Grupo")
A18: 116 | C18: Memoria RAM 32GB (2x16GB) Corsair Vengeance DDR5 6000MHz | D18: RAM | E18: 8 | F18: 135 | G18: =E18*F18 | H18: Grupo Compu & Visión | I18: Galería Compuplaza - Wilson 1251 #123 | J18: DISPONIBLE | K18: =HYPERLINK("https://m.media-amazon.com/images/I/61K5A-L+2oL._AC_SL1500_.jpg", "Ver Foto HD") | L18: =HYPERLINK("https://compuvision.pe/producto/corsair-32gb-ddr5", "Ver en Grupo")
A19: 117 | C19: Disco Sólido SSD 2TB Huadisk M.2 NVMe PCIe 4.0 | D19: Almacenamiento | E19: 1 | F19: 330 | G19: =E19*F19 | H19: Grupo Compu & Visión | I19: Galería Compuplaza - Wilson 1251 #123 | J19: STOCK BAJO | K19: =HYPERLINK("https://m.media-amazon.com/images/I/61G+d2R4bTL._AC_SL1000_.jpg", "Ver Foto HD") | L19: =HYPERLINK("https://compuvision.pe/producto/huadisk-2tb-nvme", "Ver en Grupo")
A20: 118 | C20: Disco Sólido SSD 1TB Samsung 990 Pro M.2 NVMe 2.0 | D20: Almacenamiento | E20: 4 | F20: 150 | G20: =E20*F20 | H20: Grupo Compu & Visión | I20: Galería Compuplaza - Wilson 1251 #123 | J20: DISPONIBLE | K20: =HYPERLINK("https://m.media-amazon.com/images/I/71oX6Z1T8BL._AC_SL1500_.jpg", "Ver Foto HD") | L20: =HYPERLINK("https://compuvision.pe/producto/samsung-990-pro-1tb", "Ver en Grupo")
A21: 119 | C21: Case Antec VCX100M 450W Micro-ATX 5 Fans RGB | D21: Case | E21: 1 | F21: 55 | G21: =E21*F21 | H21: SB Data | I21: Wilson 1236, Tienda 324 - Lima | J21: STOCK BAJO | K21: =HYPERLINK("https://m.media-amazon.com/images/I/71K2g7P2xTL._AC_SL1500_.jpg", "Ver Foto HD") | L21: =HYPERLINK("https://sbdata.com.pe/producto/case-antec-450w", "Ver en SB")
A22: 120 | C22: Case Antryx Elegant 630 350W ATX Mid Tower | D22: Case | E22: 7 | F22: 41.5 | G22: =E22*F22 | H22: SB Data | I22: Wilson 1236, Tienda 324 - Lima | J22: DISPONIBLE | K22: =HYPERLINK("https://m.media-amazon.com/images/I/61dG7b2S8ML._AC_SL1000_.jpg", "Ver Foto HD") | L22: =HYPERLINK("https://sbdata.com.pe/producto/case-antryx-elegant", "Ver en SB")
A23: 121 | C23: Cooler CPU Thermalright Peerless Assassin 120 SE Dual Tower | D23: Enfriamiento | E23: 2 | F23: 106.73 | G23: =E23*F23 | H23: SB Data | I23: Wilson 1236, Tienda 324 - Lima | J23: STOCK BAJO | K23: =HYPERLINK("https://m.media-amazon.com/images/I/71R2c8k1a2L._AC_SL1500_.jpg", "Ver Foto HD") | L23: =HYPERLINK("https://sbdata.com.pe/producto/thermalright-pa120", "Ver en SB")
A24: 122 | C24: Mainboard Gigabyte B760M E DDR5 LGA 1700 mATX | D24: Motherboard | E24: 4 | F24: 107.1 | G24: =E24*F24 | H24: SB Data | I24: Wilson 1236, Tienda 324 - Lima | J24: DISPONIBLE | K24: =HYPERLINK("https://m.media-amazon.com/images/I/81+c7B2527L._AC_SL1500_.jpg", "Ver Foto HD") | L24: =HYPERLINK("https://sbdata.com.pe/producto/gigabyte-b760m", "Ver en SB")
A25: 123 | C25: Mainboard Gigabyte H810M K DDR5 LGA 1851 Intel Core Ultra | D25: Motherboard | E25: 4 | F25: 95.03 | G25: =E25*F25 | H25: SB Data | I25: Wilson 1236, Tienda 324 - Lima | J25: DISPONIBLE | K25: =HYPERLINK("https://m.media-amazon.com/images/I/81+c7B2527L._AC_SL1500_.jpg", "Ver Foto HD") | L25: =HYPERLINK("https://sbdata.com.pe/producto/gigabyte-h810m", "Ver en SB")
A26: 124 | C26: Memoria RAM 16GB DDR4 Hiksemi Armor Black 3200MHz | D26: RAM | E26: 5 | F26: 139 | G26: =E26*F26 | H26: SB Data | I26: Wilson 1236, Tienda 324 - Lima | J26: DISPONIBLE | K26: =HYPERLINK("https://m.media-amazon.com/images/I/61fK9+3Zc2L._AC_SL1000_.jpg", "Ver Foto HD") | L26: =HYPERLINK("https://sbdata.com.pe/producto/hiksemi-16gb-ddr4", "Ver en SB")
A27: 125 | C27: Mainboard MSI A520M-A PRO Socket AM4 DDR4 | D27: Motherboard | E27: 15 | F27: 53.75 | G27: =E27*F27 | H27: Infotec Perú | I27: Lima - Grupo Infotec | J27: DISPONIBLE | K27: =HYPERLINK("https://m.media-amazon.com/images/I/81b2K2+d8AL._AC_SL1500_.jpg", "Ver Foto HD") | L27: =HYPERLINK("https://infotec.com.pe/producto/msi-a520m-a-pro", "Ver en Infotec")
A28: 126 | C28: Mainboard ASUS PRIME A520M-K AMD Ryzen AM4 | D28: Motherboard | E28: 12 | F28: 56.5 | G28: =E28*F28 | H28: Infotec Perú | I28: Lima - Grupo Infotec | J28: DISPONIBLE | K28: =HYPERLINK("https://m.media-amazon.com/images/I/81x-9L2C9GL._AC_SL1500_.jpg", "Ver Foto HD") | L28: =HYPERLINK("https://infotec.com.pe/producto/asus-prime-a520m-k", "Ver en Infotec")
A29: 127 | C29: Mouse Logitech G203 Lightsync Optical 8000 DPI RGB | D29: Periféricos | E29: 20 | F29: 24 | G29: =E29*F29 | H29: Rayotec | I29: RUC 20608329839 - Grupo M&V | J29: DISPONIBLE | K29: =HYPERLINK("https://m.media-amazon.com/images/I/61UxfXTUyvL._AC_SL1500_.jpg", "Ver Foto HD") | L29: =HYPERLINK("https://rayotec.pe/producto/mouse-logitech-g203", "Ver en Rayotec")
A30: 128 | C30: Fuente de Poder Gigabyte 850W 80+ Gold (GP-UD850GM) | D30: Fuentes | E30: 8 | F30: 110.8 | G30: =E30*F30 | H30: Rayotec | I30: RUC 20608329839 - Grupo M&V | J30: DISPONIBLE | K30: =HYPERLINK("https://m.media-amazon.com/images/I/71f-51v5C2L._AC_SL1500_.jpg", "Ver Foto HD") | L30: =HYPERLINK("https://rayotec.pe/producto/fuente-gigabyte-850w", "Ver en Rayotec")
C31: TOTAL ACUMULADO INVENTARIO | E31: =SUM(E3:E30) | G31: =SUM(G3:G30)

Sheet Tiendas
A1: ID | B1: Nombre Comercial de la Tienda | C1: Dirección / Ubicación Física | D1: Estado | E1: Teléfono de Contacto | F1: Garantía & Servicios | G1: Sitio Web / Catálogo Online (URL) | H1: Mapa GPS / Ubicación (URL)
A3: 1 | B3: CompuSearch Central | C3: Av. Principal 123 - San Isidro, Lima | D3: ACTIVO | E3: 555-0101 | F3: Garantía Oficial 1 año / Envíos Lima | G3: =HYPERLINK("https://compusearch.com/tiendas/central", "Web CompuSearch") | H3: =HYPERLINK("https://maps.google.com/?q=San+Isidro+Lima", "Ver Mapa GPS")
A4: 2 | B4: CompuSearch Norte | C4: Plaza Mayor 456 - Los Olivos, Lima | D4: INACTIVO | E4: 555-0202 | F4: Soporte Local | G4: =HYPERLINK("https://compusearch.com/tiendas/norte", "Web CompuSearch") | H4: =HYPERLINK("https://maps.google.com/?q=Los+Olivos+Lima", "Ver Mapa GPS")
A5: 3 | B5: pc Factory Perú | C5: Plaza San Miguel / Jockey Plaza / Comas | D5: ACTIVO | E5: +51 1 7161666 | F5: Garantía Retail / Boleta / Factura / Asesoría | G5: =HYPERLINK("https://www.pcfactory.com.pe", "Web pc") | H5: =HYPERLINK("https://maps.google.com/?q=Plaza+San+Miguel+Lima", "Ver Mapa GPS")
A6: 4 | B6: Grupo Compu & Visión | C6: Av. Garcilaso de la Vega 1251, Tienda #123 (Compuplaza) | D6: ACTIVO | E6: 987 163 458 | F6: Importación directa / Venta componentes | G6: =HYPERLINK("https://compuvision.pe", "Web Grupo") | H6: =HYPERLINK("https://maps.google.com/?q=Av.+Garcilaso+de+la+Vega+1251+Lima", "Ver Mapa GPS")
A7: 5 | B7: SB Data | C7: Av. Garcilaso de la Vega 1236, Tienda 324 (Wilson) | D7: ACTIVO | E7: 994 061 341 | F7: Armado de PC / Cotización por WhatsApp | G7: =HYPERLINK("https://sbdata.com.pe", "Web SB") | H7: =HYPERLINK("https://maps.google.com/?q=Av.+Garcilaso+de+la+Vega+1236+Lima", "Ver Mapa GPS")
A8: 6 | B8: Infotec Perú | C8: Grupo Infotec - Tienda Virtual y Física Lima | D8: ACTIVO | E8: 935 715 405 | F8: Distribuidor autorizado Intel y AMD | G8: =HYPERLINK("https://infotec.com.pe", "Web Infotec") | H8: =HYPERLINK("https://maps.google.com/?q=Infotec+Lima", "Ver Mapa GPS")
A9: 7 | B9: Rayotec | C9: RUC 20608329839 - Grupo Tecnológico M&V S.A.C. | D9: ACTIVO | E9: 974 578 820 | F9: Acepta MercadoPago / Envíos a provincia | G9: =HYPERLINK("https://rayotec.pe", "Web Rayotec") | H9: =HYPERLINK("https://maps.google.com/?q=Rayotec+Lima", "Ver Mapa GPS")
A10: 8 | B10: Memory Kings | C10: Minorista Mayorista Wilson / Tienda Online | D10: ACTIVO | E10: (01) 619-3000 | F10: Garantía extendida en componentes | G10: =HYPERLINK("https://www.memorykings.com.pe", "Web Memory") | H10: =HYPERLINK("https://maps.google.com/?q=Memory+Kings+Wilson+Lima", "Ver Mapa GPS")
A11: 9 | B11: SercoPlus | C11: Galería CompuPlaza - Wilson, Lima | D11: ACTIVO | E11: (01) 423-1122 | F11: Garantía oficial de 1 año en hardware | G11: =HYPERLINK("https://www.sercoplus.com", "Web SercoPlus") | H11: =HYPERLINK("https://maps.google.com/?q=SercoPlus+Wilson+Lima", "Ver Mapa GPS")

Sheet Usuarios
A1: ID | B1: Nombre de Usuario | C1: Correo Electrónico (Email) | D1: Rol de Sistema | E1: Estado de Cuenta | F1: Perfil Avatar (URL)
A3: 1 | B3: Admin Prueba | C3: admin@compusearch.com | D3: ADMIN | E3: ACTIVO | F3: =HYPERLINK("https://cdn-icons-png.flaticon.com/512/3135/3135715.png", "Ver Avatar")
A4: 2 | B4: Cliente Prueba | C4: cliente@compusearch.com | D4: CLIENTE | E4: ACTIVO | F4: =HYPERLINK("https://cdn-icons-png.flaticon.com/512/3135/3135768.png", "Ver Avatar")
A5: 3 | B5: Soporte Técnico | C5: soporte@compusearch.com | D5: SOPORTE | E5: ACTIVO | F5: =HYPERLINK("https://cdn-icons-png.flaticon.com/512/3135/3135789.png", "Ver Avatar")
A6: 4 | B6: Vendedor Wilson | C6: ventas@compusearch.com | D6: VENDEDOR | E6: ACTIVO | F6: =HYPERLINK("https://cdn-icons-png.flaticon.com/512/3135/3135823.png", "Ver Avatar")

Sheet Empleados
A1: ID | B1: Nombre del Empleado | C1: Puesto / Cargo | D1: Sede Asignada | E1: Estado
A3: 1 | B3: Juan Técnico | C3: Soporte Nivel 2 | D3: CompuSearch Central | E3: ACTIVO
A4: 2 | B4: María Asesora | C4: Atención al Cliente | D4: pc Factory Perú | E4: ACTIVO
A5: 3 | B5: Carlos Armador | C5: Especialista Ensamble PC | D5: SB Data Wilson | E5: ACTIVO

Sheet Incidentes
A1: ID | B1: Título del Incidente | C1: Estado | D1: Fecha Registro | E1: Prioridad
A3: 1 | B3: Fallo en servidor de base de datos | C3: PENDIENTE | D3: 2026-10-01 | E3: ALTA
A4: 2 | B4: Actualización de catálogo de componentes Wilson | C4: RESUELTO | D4: 2026-09-28 | E4: MEDIA

Sheet Categorías y Endpoints
A1: CATEGORÍAS DE PRODUCTOS DE HARDWARE
A2: ID | B2: Nombre de Categoría | C2: Código / Ícono | D2: Enlace Ícono / Imagen de Categoría (URL) | E2: Vista Previa
A3: 1 | B3: Procesadores (CPU) | C3: cpu | D3: =HYPERLINK("https://cdn-icons-png.flaticon.com/512/2004/2004699.png", "Ver Ícono CPU")
A4: 2 | B4: Tarjetas Gráficas (GPU) | C4: gpu | D4: =HYPERLINK("https://cdn-icons-png.flaticon.com/512/2004/2004724.png", "Ver Ícono GPU")
A5: 3 | B5: Memoria RAM | C5: ram | D5: =HYPERLINK("https://cdn-icons-png.flaticon.com/512/2004/2004712.png", "Ver Ícono RAM")
A6: 4 | B6: Placas Madre (Motherboard) | C6: mobo | D6: =HYPERLINK("https://cdn-icons-png.flaticon.com/512/2004/2004732.png", "Ver Ícono MOBO")
A7: 5 | B7: Almacenamiento (SSD / HDD) | C7: ssd | D7: =HYPERLINK("https://cdn-icons-png.flaticon.com/512/2004/2004705.png", "Ver Ícono SSD")
A8: 6 | B8: Gabinetes / Cases | C8: case | D8: =HYPERLINK("https://cdn-icons-png.flaticon.com/512/2004/2004718.png", "Ver Ícono CASE")
A9: 7 | B9: Sistemas de Enfriamiento | C9: cooler | D9: =HYPERLINK("https://cdn-icons-png.flaticon.com/512/2004/2004728.png", "Ver Ícono COOLER")
A10: 8 | B10: Fuentes de Poder | C10: psu | D10: =HYPERLINK("https://cdn-icons-png.flaticon.com/512/2004/2004715.png", "Ver Ícono PSU")
A11: 9 | B11: Periféricos & Accesorios | C11: perifericos | D11: =HYPERLINK("https://cdn-icons-png.flaticon.com/512/2004/2004738.png", "Ver Ícono PERIFERICOS")
A14: DEFINICIÓN DE ENDPOINTS DE LA API (MSW HANDLERS)
A15: Método HTTP | B15: Ruta de Endpoint | C15: Descripción del Handler | D15: Respuesta / Estado | E15: Mapeo Base de Datos
A16: GET | B16: /auth/me | C16: Obtener usuario autenticado actual | D16: 200 / 401 Unauthorized | E16: db.usuarios
A17: POST | B17: /auth/login | C17: Iniciar sesión y obtener mock JWT token | D17: 200 OK + token | E17: db.usuarios[0]
A18: GET | B18: /usuario/:id | C18: Consultar usuario por ID específico | D18: 200 OK / 404 Not Found | E18: db.usuarios.find()
A19: GET | B19: /categorias/todas | C19: Listado completo de categorías con íconos | D19: 200 OK | E19: Categorías con ícono
A20: GET | B20: /categorias | C20: Listado simplificado de categorías | D20: 200 OK | E20: Categorías principales
A21: GET | B21: /tiendas | C21: Listado completo de tiendas | D21: 200 OK | E21: db.tiendas
A22: GET | B22: /tiendas/verificadas | C22: Filtrar tiendas con estado ACTIVO | D22: 200 OK | E22: db.tiendas.filter(estado === ACTIVO)
A23: GET | B23: /filtro/categorias | C23: Obtener filtros por categoría | D23: 200 OK | E23: Categorías dinámicas
A24: GET | B24: /filtro/precios | C24: Obtener rango min/max de precios | D24: 200 OK { min: 0, max: 2000 } | E24: Rango de precios ($)
A25: GET | B25: /filtro/marcas | C25: Obtener marcas disponibles | D25: 200 OK ['Intel', 'NVIDIA', 'AMD'] | E25: Marcas de hardware
A26: GET | B26: /filtro/tiendas | C26: Obtener tiendas para filtrado | D26: 200 OK | E26: db.tiendas
... A30: GET | B30: /incidentes | C30: Obtener incidentes y tickets de soporte | D30: 200 OK | E30: db.incidentes
